generator/EmailGen.py
generator/NameGen.py
generator/PassGen.py
generator/PinGen.py
generator/RandomHelper.py
generator/SystemGen.py
generator/__init__.py
Generator_Random-0.0.2.dist-info/LICENSE.txt
Generator_Random-0.0.2.dist-info/METADATA
Generator_Random-0.0.2.dist-info/WHEEL
Generator_Random-0.0.2.dist-info/top_level.txt
Generator_Random-0.0.2.dist-info/RECORD
