Metadata-Version: 2.1
Name: Generator-Random
Version: 0.0.2
Summary: Generator is an All In One python package to generate random names,MAC,IP,email, password,pin and integer
Home-page: UNKNOWN
Author: Abhijeet Srivastav,  Founder Techneophyte
Author-email: abhijeetsrivastav292@gmail.com
License: UNKNOWN
Platform: UNKNOWN
Classifier: Programming Language :: Python :: 3
Classifier: License :: OSI Approved :: Apache Software License
Classifier: Operating System :: OS Independent
Requires-Python: >=3.6
